rofi_notion/__init__.py
rofi_notion/__main__.py
rofi_notion/config.py
rofi_notion/main.py
rofi_notion/manage.py
rofi_notion/settings.py
rofi_notion/transcoders.py
rofi_notion-2.1.2.dist-info/licenses/LICENSE
rofi_notion-2.1.2.dist-info/METADATA
rofi_notion-2.1.2.dist-info/WHEEL
rofi_notion-2.1.2.dist-info/entry_points.txt
rofi_notion-2.1.2.dist-info/top_level.txt
rofi_notion-2.1.2.dist-info/RECORD
