Metadata-Version: 2.4
Name: rofi-notion
Version: 2.1.2
Summary: Quickly create new Notion pages for your databases with rofi as GUI
Author-email: Arnaud Gissinger <agissing@student.42.fr>
License: MIT License
Keywords: notion.so,notion,rofi,dmenu,x11,i3
Classifier: Intended Audience :: Developers
Classifier: Intended Audience :: End Users/Desktop
Classifier: Topic :: Utilities
Classifier: License :: OSI Approved :: MIT License
Classifier: Operating System :: POSIX :: Linux
Classifier: Programming Language :: Python :: 3 :: Only
Requires-Python: >=3.7
License-File: LICENSE
Requires-Dist: prompt-toolkit>=3
Requires-Dist: notion-client==2.2.1
Requires-Dist: python-rofi==1.0.1
Requires-Dist: InquirerLib==0.0.2
Requires-Dist: argparse==1.4.0
Requires-Dist: PyYAML==6.0.2
Dynamic: license-file
